{
  "data": {
    "md5": "944c9e9d2f16640a943df06f9cca22bb",
    "path": "gui/layout_presets/appMainRole.layout",
    "root": {
      "anchor": {
        "HorizontalAlignment": "Centre",
        "VerticalAlignment": "Centre"
      },
      "children": [
        {
          "__OBJ_TYPE": "DefaultWindow",
          "children": [
            {
              "__OBJ_TYPE": "DefaultWindow",
              "anchor": {
                "HorizontalAlignment": "Centre",
                "VerticalAlignment": "Centre"
              },
              "children": [
                {
                  "__OBJ_TYPE": "StaticImage",
                  "ClippedByParent": true,
                  "id": {
                    "value": "6b19f001-4e3e-4751-9049-c46105cabe59"
                  },
                  "Image": {
                    "asset": "asset/atlas.imageset",
                    "imageset_key": "shop002 (1)",
                    "selector": "asset/atlas.imageset"
                  },
                  "name": "BgBack",
                  "size": {
                    "UDim_X": {
                      "Offect": 0,
                      "Scale": 1
                    },
                    "UDim_Y": {
                      "Offect": 0,
                      "Scale": 1
                    }
                  }
                },
                {
                  "__OBJ_TYPE": "StaticImage",
                  "anchor": {
                    "HorizontalAlignment": "Centre",
                    "VerticalAlignment": "Bottom"
                  },
                  "ClippedByParent": true,
                  "id": {
                    "value": "0f822f58-c553-4c58-8c50-4fa7005e4ddb"
                  },
                  "Image": {
                    "asset": "",
                    "selector": ""
                  },
                  "name": "BgBottom",
                  "size": {
                    "UDim_X": {
                      "Offect": 0,
                      "Scale": 1
                    },
                    "UDim_Y": {
                      "Offect": 10
                    }
                  }
                },
                {
                  "__OBJ_TYPE": "StaticImage",
                  "anchor": {
                    "HorizontalAlignment": "Centre",
                    "VerticalAlignment": "Centre"
                  },
                  "ClippedByParent": true,
                  "id": {
                    "value": "3e98623f-9d33-4acb-ac69-51a4a76b731d"
                  },
                  "Image": {
                    "asset": "asset/Texture/Gui/imagesets/role_Panel.imageset",
                    "imageset_key": "cut_off",
                    "selector": "asset/Texture/Gui/imagesets/role_Panel.imageset"
                  },
                  "name": "Cut",
                  "size": {
                    "UDim_X": {
                      "Offect": 5
                    },
                    "UDim_Y": {
                      "Offect": 459
                    }
                  }
                }
              ],
              "ClippedByParent": true,
              "id": {
                "value": "f1cdd9a0-c3a5-4754-933d-de8719de0ec4"
              },
              "name": "BG",
              "size": {
                "UDim_X": {
                  "Offect": 0,
                  "Scale": 1
                },
                "UDim_Y": {
                  "Offect": 0,
                  "Scale": 1
                }
              }
            },
            {
              "__OBJ_TYPE": "ScrollableView",
              "anchor": {
                "VerticalAlignment": "Centre"
              },
              "BackGroundImage": {
                "asset": "",
                "selector": ""
              },
              "children": [
                {
                  "__OBJ_TYPE": "GridView",
                  "ClippedByParent": true,
                  "id": {
                    "value": "a4d24c0e-3b77-49f9-8952-4d33aac9aae6"
                  },
                  "name": "GridLayout",
                  "size": {
                    "UDim_X": {
                      "Scale": 1
                    },
                    "UDim_Y": {
                      "Scale": 1
                    }
                  }
                }
              ],
              "ClippedByParent": true,
              "ForceHorzScrollbar": false,
              "ForceVertScrollbar": false,
              "id": {
                "value": "52f4bd69-4c63-4fae-863e-313974a90e67"
              },
              "name": "LeftScrollableView",
              "pos": {
                "UDim_X": {
                  "Scale": 0.05
                },
                "UDim_Y": {
                  "Scale": 0.05
                }
              },
              "size": {
                "UDim_X": {
                  "Offect": 0,
                  "Scale": 0.5
                },
                "UDim_Y": {
                  "Offect": 0,
                  "Scale": 0.7
                }
              }
            },
            {
              "__OBJ_TYPE": "ScrollableView",
              "anchor": {
                "HorizontalAlignment": "Right",
                "VerticalAlignment": "Centre"
              },
              "BackGroundImage": {
                "asset": "",
                "selector": ""
              },
              "children": [
                {
                  "__OBJ_TYPE": "GridView",
                  "ClippedByParent": true,
                  "id": {
                    "value": "f1876147-55ac-43cd-b184-2af76689bfce"
                  },
                  "name": "GridLayout",
                  "size": {
                    "UDim_X": {
                      "Scale": 1
                    },
                    "UDim_Y": {
                      "Scale": 1
                    }
                  }
                }
              ],
              "ClippedByParent": true,
              "ForceHorzScrollbar": false,
              "ForceVertScrollbar": false,
              "id": {
                "value": "2578018a-17f6-402b-8b4c-b80b8ce22828"
              },
              "name": "RightScrollableView",
              "size": {
                "UDim_X": {
                  "Offect": 0,
                  "Scale": 0.49
                },
                "UDim_Y": {
                  "Offect": 0,
                  "Scale": 0.97
                }
              }
            },
            {
              "__OBJ_TYPE": "DefaultWindow",
              "ClippedByParent": true,
              "id": {
                "value": "93b053b3-63b1-4feb-a14e-703a4ec92755"
              },
              "name": "LeftLayout",
              "pos": {
                "UDim_X": {
                  "Scale": 0.05
                },
                "UDim_Y": {
                  "Scale": 0.2
                }
              },
              "size": {
                "UDim_X": {
                  "Offect": 0,
                  "Scale": 0.45
                },
                "UDim_Y": {
                  "Offect": 0,
                  "Scale": 0.7
                }
              }
            },
            {
              "__OBJ_TYPE": "DefaultWindow",
              "anchor": {
                "HorizontalAlignment": "Right"
              },
              "ClippedByParent": true,
              "id": {
                "value": "e1ed603b-2fba-4b89-9f13-d5b6e6e2f51d"
              },
              "name": "RightLayout",
              "size": {
                "UDim_X": {
                  "Offect": 0,
                  "Scale": 0.49
                },
                "UDim_Y": {
                  "Offect": 0,
                  "Scale": 0.97
                }
              }
            }
          ],
          "ClippedByParent": true,
          "id": {
            "value": "651c61e5-9e50-413a-8e1b-eccdd3508fdc"
          },
          "name": "Main",
          "pos": {
            "UDim_X": {
              "Offect": 206
            },
            "UDim_Y": {
              "Offect": 92
            }
          },
          "size": {
            "UDim_X": {
              "Offect": 1000
            },
            "UDim_Y": {
              "Offect": 537.8
            }
          }
        },
        {
          "__OBJ_TYPE": "DefaultWindow",
          "children": [
            {
              "__OBJ_TYPE": "StaticImage",
              "ClippedByParent": true,
              "id": {
                "value": "fbdaf45c-d9a4-4ec5-a7ad-38b88567a091"
              },
              "Image": {
                "asset": "asset/Texture/Gui/imagesets/role_Panel.imageset",
                "imageset_key": "tab_left_top_bg",
                "selector": "asset/Texture/Gui/imagesets/role_Panel.imageset"
              },
              "name": "TopBg",
              "size": {
                "UDim_X": {
                  "Offect": 0,
                  "Scale": 1
                },
                "UDim_Y": {
                  "Offect": 46
                }
              }
            },
            {
              "__OBJ_TYPE": "ScrollableView",
              "anchor": {
                "VerticalAlignment": "Bottom"
              },
              "BackGroundImage": {
                "asset": "",
                "selector": ""
              },
              "children": [
                {
                  "__OBJ_TYPE": "GridView",
                  "ClippedByParent": true,
                  "id": {
                    "value": "50f44250-4106-4b8b-a1ab-f1a7e75f8444"
                  },
                  "name": "GridLayout",
                  "size": {
                    "UDim_X": {
                      "Scale": 1
                    },
                    "UDim_Y": {
                      "Scale": 1
                    }
                  }
                }
              ],
              "ClippedByParent": true,
              "ForceHorzScrollbar": false,
              "ForceVertScrollbar": false,
              "id": {
                "value": "fa290d67-8cf9-455f-9b7a-0936e50b5437"
              },
              "name": "RoleScrollableView",
              "size": {
                "UDim_X": {
                  "Offect": 0,
                  "Scale": 1
                },
                "UDim_Y": {
                  "Offect": -46,
                  "Scale": 1
                }
              }
            }
          ],
          "ClippedByParent": true,
          "id": {
            "value": "c9fc3c98-a99c-4cdb-a1db-27fa3679cd70"
          },
          "name": "LeftLayout",
          "pos": {
            "UDim_X": {
              "Offect": 53
            },
            "UDim_Y": {
              "Offect": 93
            }
          },
          "size": {
            "UDim_X": {
              "Offect": 154
            },
            "UDim_Y": {
              "Offect": 537
            }
          }
        },
        {
          "__OBJ_TYPE": "DefaultWindow",
          "children": [
            {
              "__OBJ_TYPE": "StaticImage",
              "ClippedByParent": true,
              "id": {
                "value": "ec3f57f3-6ff5-460e-9a70-81185e2e35bc"
              },
              "Image": {
                "asset": "asset/Texture/Gui/imagesets/role_Panel.imageset",
                "imageset_key": "bg_title",
                "selector": "asset/Texture/Gui/imagesets/role_Panel.imageset"
              },
              "name": "BG",
              "size": {
                "UDim_X": {
                  "Offect": 0,
                  "Scale": 1
                },
                "UDim_Y": {
                  "Offect": 0,
                  "Scale": 1
                }
              }
            },
            {
              "__OBJ_TYPE": "StaticText",
              "anchor": {
                "HorizontalAlignment": "Right"
              },
              "ClippedByParent": true,
              "id": {
                "value": "d6a5f1dd-ac99-4cec-b34d-83af6e55df3b"
              },
              "size": {
                "UDim_X": {
                  "Offect": -50,
                  "Scale": 1
                },
                "UDim_Y": {
                  "Offect": 0,
                  "Scale": 1
                }
              },
              "Text": "Text",
              "TextColours": {
                "b": 255,
                "g": 255,
                "r": 255
              },
              "VertFormatting": "BottomAligned",
              "word_warpped": false
            }
          ],
          "ClippedByParent": true,
          "id": {
            "value": "0a6025f3-cf5b-42a7-950a-bc6a2c435be5"
          },
          "name": "TopLayout",
          "pos": {
            "UDim_X": {
              "Offect": 206
            },
            "UDim_Y": {
              "Offect": 53
            }
          },
          "size": {
            "UDim_X": {
              "Offect": 298
            },
            "UDim_Y": {
              "Offect": 40
            }
          }
        },
        {
          "__OBJ_TYPE": "Button",
          "ClippedByParent": true,
          "DisabledImage": {
            "asset": "asset/Texture/Gui/imagesets/role_Panel.imageset",
            "imageset_key": "icon_close",
            "selector": "asset/Texture/Gui/imagesets/role_Panel.imageset"
          },
          "HoverImage": {
            "asset": "asset/Texture/Gui/imagesets/role_Panel.imageset",
            "imageset_key": "icon_close",
            "selector": "asset/Texture/Gui/imagesets/role_Panel.imageset"
          },
          "id": {
            "value": "ecb2785b-a6ae-4c82-82a4-4569d868a948"
          },
          "name": "Close",
          "NormalImage": {
            "asset": "asset/Texture/Gui/imagesets/role_Panel.imageset",
            "imageset_key": "icon_close",
            "selector": "asset/Texture/Gui/imagesets/role_Panel.imageset"
          },
          "pos": {
            "UDim_X": {
              "Offect": 1152
            },
            "UDim_Y": {
              "Offect": 39
            }
          },
          "PushedImage": {
            "asset": "asset/Texture/Gui/imagesets/role_Panel.imageset",
            "imageset_key": "icon_close",
            "selector": "asset/Texture/Gui/imagesets/role_Panel.imageset"
          },
          "size": {
            "UDim_X": {
              "Offect": 54
            },
            "UDim_Y": {
              "Offect": 54
            }
          },
          "Text": ""
        }
      ],
      "ClippedByParent": true,
      "id": {
        "value": "cd834334-2587-4937-9b45-86318d5b310f"
      },
      "size": {
        "UDim_X": {
          "Offect": 0,
          "Scale": 1
        },
        "UDim_Y": {
          "Offect": 0,
          "Scale": 1
        }
      }
    }
  },
  "meta": {
    "EXPORT": {
      "layout": "944c9e9d2f16640a943df06f9cca22bb",
      "triggers.bts": "d1fd7037f4941cd1b8cbfb94bb926990"
    },
    "VERSION": "0.22"
  }
}